{
  "version": "1.2.0",
  "updateType": "mandatory",
  "mandatory": true,
  "minimumSupportedVersion": "1.0.0",
  "downloadUrl": "https://github.com/azizalmassah2/alpha-manager-updates/releases/download/v1.1.0/AlphaManagerSetup_v1.1.0.exe",
  "sha256": "90c3b69cf4b34163eda1efd8283654eee4816ae3777254e8811f703d9dfd9c2f",
  "fileSize": 16280220,
  "releaseDate": "2026-07-16",
  "releaseNotes": [
    "تطوير نظام التراخيص وعرض تفاصيل تشخيصية دقيقة للغاية عند فشل التفعيل لمعرفة السبب فوراً.",
    "تعريب واجهة الترخيص واستبدال الكلمة الإنجليزية licensed بكلمة 'مرخص' باللغة العربية.",
    "حل مشكلة تعليق ملف التثبيت المُنزل (File Lock) ليعمل التثبيت التلقائي فور انتهاء التحميل 100%.",
    "إضافة وحدة إدارة صفحات تسجيل الدخول (Hotspot) للتحكم الكامل بالقوالب وتعديلها.",
    "دعم فك تشفير قالب ALFA وتعديله وتخصيصه مباشرة من داخل البرنامج ومعاينته محلياً.",
    "تحسين وتطوير أداة رفع ملفات الـ Hotspot عبر بروتوكول FTP بسرعة واستقرار.",
    "حل مشكلة التداخل البصري بشكل كامل بين شاشة الـ Splash ونافذة التحديث.",
    "تحسينات عامة على سرعة استجابة واجهة المستخدم واستقرار قواعد البيانات."
  ],
  "message": "يحتوي هذا الإصدار على تعريب الواجهات وإصلاحات قفل الملفات عند التحديث ونظام تشخيص التراخيص الجديد، الترقية إجبارية للمتابعة.",
  "enabled": true
}
